PyInstaller/__init__.py
PyInstaller/__main__.py
PyInstaller/_recursion_too_deep_message.py
PyInstaller/_shared_with_waf.py
PyInstaller/compat.py
PyInstaller/config.py
PyInstaller/configure.py
PyInstaller/exceptions.py
PyInstaller/log.py
PyInstaller/archive/__init__.py
PyInstaller/archive/pyz_crypto.py
PyInstaller/archive/readers.py
PyInstaller/archive/writers.py
PyInstaller/bootloader/Darwin-64bit/run
PyInstaller/bootloader/Darwin-64bit/run_d
PyInstaller/bootloader/Darwin-64bit/runw
PyInstaller/bootloader/Darwin-64bit/runw_d
PyInstaller/bootloader/Linux-32bit-intel/run
PyInstaller/bootloader/Linux-32bit-intel/run_d
PyInstaller/bootloader/Linux-64bit-intel/run
PyInstaller/bootloader/Linux-64bit-intel/run_d
PyInstaller/bootloader/Windows-32bit-intel/run.exe
PyInstaller/bootloader/Windows-32bit-intel/run_d.exe
PyInstaller/bootloader/Windows-32bit-intel/runw.exe
PyInstaller/bootloader/Windows-32bit-intel/runw_d.exe
PyInstaller/bootloader/Windows-64bit-intel/run.exe
PyInstaller/bootloader/Windows-64bit-intel/run_d.exe
PyInstaller/bootloader/Windows-64bit-intel/runw.exe
PyInstaller/bootloader/Windows-64bit-intel/runw_d.exe
PyInstaller/bootloader/images/icon-console.icns
PyInstaller/bootloader/images/icon-console.ico
PyInstaller/bootloader/images/icon-windowed.icns
PyInstaller/bootloader/images/icon-windowed.ico
PyInstaller/building/__init__.py
PyInstaller/building/api.py
PyInstaller/building/build_main.py
PyInstaller/building/datastruct.py
PyInstaller/building/icon.py
PyInstaller/building/makespec.py
PyInstaller/building/osx.py
PyInstaller/building/splash.py
PyInstaller/building/splash_templates.py
PyInstaller/building/templates.py
PyInstaller/building/utils.py
PyInstaller/depend/__init__.py
PyInstaller/depend/analysis.py
PyInstaller/depend/bindepend.py
PyInstaller/depend/bytecode.py
PyInstaller/depend/dylib.py
PyInstaller/depend/imphook.py
PyInstaller/depend/imphookapi.py
PyInstaller/depend/utils.py
PyInstaller/fake-modules/pyi_splash.py
custom_fork_pyinstaller_1-6.5.0.dist-info/COPYING.txt
custom_fork_pyinstaller_1-6.5.0.dist-info/METADATA
custom_fork_pyinstaller_1-6.5.0.dist-info/WHEEL
custom_fork_pyinstaller_1-6.5.0.dist-info/entry_points.txt
custom_fork_pyinstaller_1-6.5.0.dist-info/top_level.txt
custom_fork_pyinstaller_1-6.5.0.dist-info/RECORD
